Octrapy/__init__.py
Octrapy/abc.py
Octrapy/chat.py
Octrapy/client.py
Octrapy/errors.py
Octrapy/file.py
Octrapy/http.py
Octrapy/message.py
Octrapy/poll.py
Octrapy/user.py
Octrapy/utils.py
Octrapy/ext/commands/__init__.py
Octrapy/ext/commands/bot.py
Octrapy/ext/commands/cog.py
Octrapy/ext/commands/context.py
Octrapy/ext/commands/converter.py
Octrapy/ext/commands/core.py
Octrapy/ext/commands/errors.py
Octrapy/ext/commands/help.py
Octra.py-1.8.68.dist-info/METADATA
Octra.py-1.8.68.dist-info/WHEEL
Octra.py-1.8.68.dist-info/top_level.txt
Octra.py-1.8.68.dist-info/RECORD
