Metadata-Version: 2.1
Name: Octra.py
Version: 1.8.68
Summary: An async API wrapper for Octra bot API in Python
Home-page: https://github.com/Octra/Octra.py
Author: Akash
License: UNKNOWN
Project-URL: Documentation, https://Octrapy.readthedocs.io
Project-URL: Issue tracker, https://github.com/Octra/Octra.py/issues
Platform: UNKNOWN
Classifier: Development Status :: 3 - Alpha
Classifier: Programming Language :: Python :: 3.7
Classifier: Programming Language :: Python :: 3.8
Classifier: Programming Language :: Python :: 3.9
Classifier: License :: OSI Approved :: MIT License
Classifier: Intended Audience :: Developers
Classifier: Operating System :: OS Independent
Requires-Python: >=3.7
Requires-Dist: TgCrypto
Provides-Extra: docs
Requires-Dist: sphinx (==2.4.3) ; extra == 'docs'
Requires-Dist: sphinx-rtd-theme ; extra == 'docs'
Requires-Dist: sphinxcontrib-trio (==1.1.1) ; extra == 'docs'
Requires-Dist: sphinxcontrib-websupport ; extra == 'docs'
